naff/__init__.py
naff/py.typed
naff/api/__init__.py
naff/api/events/__init__.py
naff/api/events/base.py
naff/api/events/discord.py
naff/api/events/internal.py
naff/api/events/processors/__init__.py
naff/api/events/processors/_template.py
naff/api/events/processors/_template.pyi
naff/api/events/processors/auto_mod.py
naff/api/events/processors/channel_events.py
naff/api/events/processors/guild_events.py
naff/api/events/processors/integrations.py
naff/api/events/processors/member_events.py
naff/api/events/processors/message_events.py
naff/api/events/processors/reaction_events.py
naff/api/events/processors/role_events.py
naff/api/events/processors/stage_events.py
naff/api/events/processors/thread_events.py
naff/api/events/processors/user_events.py
naff/api/events/processors/voice_events.py
naff/api/gateway/__init__.py
naff/api/gateway/gateway.py
naff/api/gateway/state.py
naff/api/gateway/websocket.py
naff/api/http/__init__.py
naff/api/http/http_client.py
naff/api/http/route.py
naff/api/http/http_requests/__init__.py
naff/api/http/http_requests/bot.py
naff/api/http/http_requests/channels.py
naff/api/http/http_requests/emojis.py
naff/api/http/http_requests/guild.py
naff/api/http/http_requests/interactions.py
naff/api/http/http_requests/members.py
naff/api/http/http_requests/messages.py
naff/api/http/http_requests/reactions.py
naff/api/http/http_requests/scheduled_events.py
naff/api/http/http_requests/stickers.py
naff/api/http/http_requests/threads.py
naff/api/http/http_requests/users.py
naff/api/http/http_requests/webhooks.py
naff/api/voice/__init__.py
naff/api/voice/audio.py
naff/api/voice/encryption.py
naff/api/voice/opus.py
naff/api/voice/player.py
naff/api/voice/voice_gateway.py
naff/bin/opus-x64.dll
naff/bin/opus-x86.dll
naff/client/__init__.py
naff/client/auto_shard_client.py
naff/client/client.py
naff/client/const.py
naff/client/errors.py
naff/client/smart_cache.py
naff/client/mixins/__init__.py
naff/client/mixins/send.py
naff/client/mixins/serialization.py
naff-2.1.0.dist-info/LICENSE
naff-2.1.0.dist-info/METADATA
naff-2.1.0.dist-info/WHEEL
naff-2.1.0.dist-info/top_level.txt
naff-2.1.0.dist-info/RECORD
