Metadata-Version: 2.1
Name: naff
Version: 2.1.0
Summary: Not another freaking fork
Home-page: https://github.com/Discord-Snake-Pit/NAFF
Author: LordOfPolls
Author-email: naff@lordofpolls.com
Project-URL: Discord, https://discord.gg/hpfNhH8BsY
Project-URL: Documentation, https://naff-docs.readthedocs.io/en/latest/
Classifier: Development Status :: 3 - Alpha
Classifier: Framework :: AsyncIO
Classifier: Framework :: aiohttp
Classifier: Intended Audience :: Developers
Classifier: License :: OSI Approved :: MIT License
Classifier: Natural Language :: English
Classifier: Operating System :: OS Independent
Classifier: Programming Language :: Python :: 3
Classifier: Programming Language :: Python :: 3.10
Classifier: Topic :: Software Development :: Libraries
Classifier: Topic :: Software Development :: Libraries :: Python Modules
Classifier: Topic :: Documentation
Classifier: Typing :: Typed
Requires-Python: >=3.10
License-File: LICENSE
Requires-Dist: aiohttp
Requires-Dist: attrs (>=22.1.0)
Requires-Dist: discord-typings (>=0.5.1)
Requires-Dist: emoji
Requires-Dist: tomli
Provides-Extra: all
Requires-Dist: PyNaCl (<1.6,>=1.5.0) ; extra == 'all'
Requires-Dist: aiodns ; extra == 'all'
Requires-Dist: orjson ; extra == 'all'
Requires-Dist: Brotli ; extra == 'all'
Requires-Dist: sentry-sdk ; extra == 'all'
Requires-Dist: jurigged ; extra == 'all'
Provides-Extra: docs
Requires-Dist: PyNaCl (<1.6,>=1.5.0) ; extra == 'docs'
Requires-Dist: aiodns ; extra == 'docs'
Requires-Dist: orjson ; extra == 'docs'
Requires-Dist: Brotli ; extra == 'docs'
Requires-Dist: sentry-sdk ; extra == 'docs'
Requires-Dist: jurigged ; extra == 'docs'
Requires-Dist: mkdocs-autorefs ; extra == 'docs'
Requires-Dist: mkdocs-awesome-pages-plugin ; extra == 'docs'
Requires-Dist: mkdocs-material ; extra == 'docs'
Requires-Dist: mkdocstrings-python ; extra == 'docs'
Requires-Dist: mkdocs-minify-plugin ; extra == 'docs'
Requires-Dist: mkdocs-git-committers-plugin-2 ; extra == 'docs'
Requires-Dist: mkdocs-git-revision-date-localized-plugin ; extra == 'docs'
Provides-Extra: jurigged
Requires-Dist: jurigged ; extra == 'jurigged'
Provides-Extra: sentry
Requires-Dist: sentry-sdk ; extra == 'sentry'
Provides-Extra: speedup
Requires-Dist: aiodns ; extra == 'speedup'
Requires-Dist: orjson ; extra == 'speedup'
Requires-Dist: Brotli ; extra == 'speedup'
Provides-Extra: tests
Requires-Dist: pytest ; extra == 'tests'
Requires-Dist: pytest-recording ; extra == 'tests'
Requires-Dist: pytest-asyncio ; extra == 'tests'
Requires-Dist: pytest-cov ; extra == 'tests'
Requires-Dist: python-dotenv ; extra == 'tests'
Requires-Dist: typeguard ; extra == 'tests'
Provides-Extra: voice
Requires-Dist: PyNaCl (<1.6,>=1.5.0) ; extra == 'voice'
